observer_pattern.py
observer_pattern-1.0.0.dist-info/LICENSE
observer_pattern-1.0.0.dist-info/METADATA
observer_pattern-1.0.0.dist-info/WHEEL
observer_pattern-1.0.0.dist-info/top_level.txt
observer_pattern-1.0.0.dist-info/RECORD
